mikkoo/__init__.py
mikkoo/controller.py
mikkoo/mcp.py
mikkoo/state.py
mikkoo/stats.py
mikkoo/worker.py
mikkoo-2.0.0.dist-info/LICENSE
mikkoo-2.0.0.dist-info/METADATA
mikkoo-2.0.0.dist-info/WHEEL
mikkoo-2.0.0.dist-info/entry_points.txt
mikkoo-2.0.0.dist-info/top_level.txt
mikkoo-2.0.0.dist-info/zip-safe
mikkoo-2.0.0.dist-info/RECORD
