Metadata-Version: 2.1
Name: mikkoo
Version: 2.0.0
Summary: Mikkoo is a PgQ to RabbitMQ Relay
Home-page: https://github.com/gmr/mikkoo
Author: Gavin M. Roy
Author-email: gavinmroy@gmail.com
License: BSD 3-Clause License
Project-URL: Bug Tracker, https://github.com/gmr/mikkoo/issues
Project-URL: Documentation, https://mikkoo.readthedocs.io
Project-URL: Source Code, https://github.com/gmr/mikkoo/
Keywords: amqp,postgres,postgresql,rabbitmq
Classifier: Development Status :: 5 - Production/Stable
Classifier: Intended Audience :: Developers
Classifier: License :: OSI Approved :: BSD License
Classifier: Natural Language :: English
Classifier: Operating System :: OS Independent
Classifier: Programming Language :: Python :: 3
Classifier: Programming Language :: Python :: 3.11
Classifier: Programming Language :: Python :: 3 :: Only
Classifier: Topic :: Communications
Classifier: Topic :: Internet
Classifier: Topic :: Software Development
Classifier: Typing :: Typed
Requires-Python: >=3.9
License-File: LICENSE
Requires-Dist: arrow (<2,>=1.2.3)
Requires-Dist: helper (<3,>=2.5.0)
Requires-Dist: pika (<2,>=1.2.0)
Requires-Dist: psutil (<6,>=5.9.1)
Requires-Dist: psycopg (<4,>3)
Requires-Dist: pyyaml (<6,>=5.3.1)
Requires-Dist: uuid7
Provides-Extra: sentry
Requires-Dist: sentry-sdk ; extra == 'sentry'
Provides-Extra: statsd
Requires-Dist: sprockets-statsd ; extra == 'statsd'
Provides-Extra: testing
Requires-Dist: bandit ; extra == 'testing'
Requires-Dist: coverage ; extra == 'testing'
Requires-Dist: flake8 ; extra == 'testing'
Requires-Dist: flake8-comprehensions ; extra == 'testing'
Requires-Dist: flake8-deprecated ; extra == 'testing'
Requires-Dist: flake8-import-order ; extra == 'testing'
Requires-Dist: flake8-print ; extra == 'testing'
Requires-Dist: flake8-quotes ; extra == 'testing'
Requires-Dist: flake8-rst-docstrings ; extra == 'testing'
Requires-Dist: flake8-tuple ; extra == 'testing'
Requires-Dist: sentry-sdk ; extra == 'testing'
Requires-Dist: sphinx ; extra == 'testing'
Requires-Dist: sprockets-statsd ; extra == 'testing'
Requires-Dist: types-pika ; extra == 'testing'
Requires-Dist: yapf ; extra == 'testing'
